app/__init__.py
app/cli.py
app/logger.py
app/main.py
app/manager.py
app/timer.py
devpair-1.1.18.dist-info/entry_points.txt
devpair-1.1.18.dist-info/LICENSE
devpair-1.1.18.dist-info/WHEEL
devpair-1.1.18.dist-info/METADATA
devpair-1.1.18.dist-info/RECORD
