Metadata-Version: 2.1
Name: devpair
Version: 1.1.18
Summary: Pair script that manage a pair programming session using git.
License: MIT
Author: raphael.kieling
Author-email: raphael.kieling@telus.com
Requires-Python: >=3.7,<4.0
Classifier: License :: OSI Approved :: MIT License
Classifier: Programming Language :: Python :: 3
Classifier: Programming Language :: Python :: 3.7
Classifier: Programming Language :: Python :: 3.8
Classifier: Programming Language :: Python :: 3.9
Classifier: Programming Language :: Python :: 3.10
Classifier: Programming Language :: Python :: 3.11
Requires-Dist: GitPython (>=3.1.29,<4.0.0)
Requires-Dist: click (>=8.0.4,<9.0.0)
Requires-Dist: coveralls (>=3.3.1,<4.0.0)
Requires-Dist: cowsay (>=5.0,<6.0)
Requires-Dist: loguru (>=0.6.0,<0.7.0)
Requires-Dist: python-dateutil (>=2.8.2,<3.0.0)
